ml/__init__.py
ml/setup.py
ml/utils.py
ml/datasets/__init__.py
ml/datasets/ucf101.py
ml/datasets/ucf50.py
ml/datasets/utils.py
ml/dynamic_images/__init__.py
ml/dynamic_images/utils.py
ml/tf1/__init__.py
ml/tf1/capsnet/__init__.py
ml/tf1/capsnet/layers.py
ml/tf1/capsnet/losses.py
ml/tf1/capsnet/models.py
ml/tf1/capsnet/utils.py
ml/tf2/__init__.py
ml/tf2/capsnet/__init__.py
ml/tf2/capsnet/layers.py
ml/tf2/capsnet/losses.py
ml/tf2/capsnet/models.py
ml/tf2/capsnet/utils.py
capsnet_classification_libs-0.0.2a0.dist-info/METADATA
capsnet_classification_libs-0.0.2a0.dist-info/WHEEL
capsnet_classification_libs-0.0.2a0.dist-info/top_level.txt
capsnet_classification_libs-0.0.2a0.dist-info/RECORD
